powerlift/__init__.py
powerlift/_version.py
powerlift/bench/__init__.py
powerlift/bench/benchmark.py
powerlift/bench/experiment.py
powerlift/bench/store.py
powerlift/db/__init__.py
powerlift/db/actions.py
powerlift/db/schema.py
powerlift/executors/__init__.py
powerlift/executors/azure_ci.py
powerlift/executors/base.py
powerlift/executors/docker.py
powerlift/executors/localmachine.py
powerlift/measures/__init__.py
powerlift/measures/task_measures.py
powerlift-0.1.12.dist-info/LICENSE
powerlift-0.1.12.dist-info/METADATA
powerlift-0.1.12.dist-info/WHEEL
powerlift-0.1.12.dist-info/top_level.txt
powerlift-0.1.12.dist-info/RECORD
