Metadata-Version: 2.1
Name: powerlift
Version: 0.1.12
Summary: Interactive Benchmarking for Machine Learning.
Home-page: https://github.com/interpretml/interpret
Author: The InterpretML Contributors
Author-email: interpret@microsoft.com
Project-URL: Bug Tracker, https://github.com/interpretml/interpret/issues
Classifier: Programming Language :: Python :: 3
Classifier: License :: OSI Approved :: MIT License
Classifier: Operating System :: OS Independent
Requires-Python: >=3.7
License-File: LICENSE
Requires-Dist: SQLAlchemy>=1.4
Requires-Dist: sqlalchemy-utils>=0.38
Requires-Dist: tqdm
Requires-Dist: fastparquet
Requires-Dist: stopit
Requires-Dist: pandas
Requires-Dist: numpy
Requires-Dist: pytz
Provides-Extra: aci
Requires-Dist: msrestazure; extra == "aci"
Requires-Dist: azure-common; extra == "aci"
Requires-Dist: azure-mgmt-sql; extra == "aci"
Requires-Dist: azure-mgmt-resource; extra == "aci"
Requires-Dist: azure-mgmt-containerinstance; extra == "aci"
Requires-Dist: azure-mgmt-authorization; extra == "aci"
Requires-Dist: azure-identity; extra == "aci"
Provides-Extra: datasets
Requires-Dist: pmlb>=1.0; extra == "datasets"
Requires-Dist: openml>=0.12; extra == "datasets"
Requires-Dist: catboost; extra == "datasets"
Provides-Extra: docker
Requires-Dist: docker; extra == "docker"
Provides-Extra: mssql
Requires-Dist: pyodbc; extra == "mssql"
Provides-Extra: postgres
Requires-Dist: psycopg2>=2.9; extra == "postgres"
Provides-Extra: testing
Requires-Dist: pytest; extra == "testing"
Requires-Dist: pytest-cov; extra == "testing"
Requires-Dist: scikit-learn; extra == "testing"
Requires-Dist: python-dotenv; extra == "testing"
Requires-Dist: pytest-xdist; extra == "testing"
